streamlit_quill/__init__.py
streamlit_quill/frontend/build/asset-manifest.json
streamlit_quill/frontend/build/bootstrap.min.css
streamlit_quill/frontend/build/index.html
streamlit_quill/frontend/build/precache-manifest.57ec02c411682e3b05a6e79e0ca7c2b6.js
streamlit_quill/frontend/build/service-worker.js
streamlit_quill/frontend/build/style.css
streamlit_quill/frontend/build/static/css/2.e42673f0.chunk.css
streamlit_quill/frontend/build/static/css/2.e42673f0.chunk.css.map
streamlit_quill/frontend/build/static/js/2.866808a0.chunk.js
streamlit_quill/frontend/build/static/js/2.866808a0.chunk.js.LICENSE.txt
streamlit_quill/frontend/build/static/js/2.866808a0.chunk.js.map
streamlit_quill/frontend/build/static/js/main.d916db36.chunk.js
streamlit_quill/frontend/build/static/js/main.d916db36.chunk.js.map
streamlit_quill/frontend/build/static/js/runtime-main.44d30fc2.js
streamlit_quill/frontend/build/static/js/runtime-main.44d30fc2.js.map
streamlit_quill/frontend/build/static/media/KaTeX_AMS-Regular.2dbe16b4.ttf
streamlit_quill/frontend/build/static/media/KaTeX_AMS-Regular.38a68f7d.woff2
streamlit_quill/frontend/build/static/media/KaTeX_AMS-Regular.7d307e83.woff
streamlit_quill/frontend/build/static/media/KaTeX_Caligraphic-Bold.33d26881.ttf
streamlit_quill/frontend/build/static/media/KaTeX_Caligraphic-Bold.342b2969.woff2
streamlit_quill/frontend/build/static/media/KaTeX_Caligraphic-Bold.9634168f.woff
streamlit_quill/frontend/build/static/media/KaTeX_Caligraphic-Regular.00029fb4.woff
streamlit_quill/frontend/build/static/media/KaTeX_Caligraphic-Regular.5e7940b4.ttf
streamlit_quill/frontend/build/static/media/KaTeX_Caligraphic-Regular.b5004973.woff2
streamlit_quill/frontend/build/static/media/KaTeX_Fraktur-Bold.4de87d40.woff
streamlit_quill/frontend/build/static/media/KaTeX_Fraktur-Bold.7a3757c0.woff2
streamlit_quill/frontend/build/static/media/KaTeX_Fraktur-Bold.ed330126.ttf
streamlit_quill/frontend/build/static/media/KaTeX_Fraktur-Regular.450cc4d9.woff2
streamlit_quill2-0.0.5.dist-info/LICENSE
streamlit_quill2-0.0.5.dist-info/METADATA
streamlit_quill2-0.0.5.dist-info/WHEEL
streamlit_quill2-0.0.5.dist-info/top_level.txt
streamlit_quill2-0.0.5.dist-info/RECORD
