Metadata-Version: 2.1
Name: streamlit-quill2
Version: 0.0.5
Summary: Quill component for Streamlit
Home-page: https://github.com/bkdevinci/streamlit-quill
Author: bkdevinci
Author-email: 
License: MIT
Classifier: License :: OSI Approved :: MIT License
Classifier: Programming Language :: Python :: 3
Requires-Python: >=3.6
License-File: LICENSE
Requires-Dist: streamlit>=0.63
